MANIFEST.in
README.md
setup.py
src/li_api_flask/__init__.py
src/li_api_flask/api.py
src/li_api_flask/http_cache.py
src/li_api_flask/restful.py
src/li_api_flask/seguranca.py
src/li_api_flask/serializacao.py
src/li_api_flask/settings.py
src/li_api_flask.egg-info/PKG-INFO
src/li_api_flask.egg-info/SOURCES.txt
src/li_api_flask.egg-info/dependency_links.txt
src/li_api_flask.egg-info/pbr.json
src/li_api_flask.egg-info/requires.txt
src/li_api_flask.egg-info/top_level.txt