Metadata-Version: 1.1
Name: li-api-flask
Version: 0.1.10
Summary: Loja Integrada's API Flask
Home-page: https://github.com/lojaintegrada/LI-Api-Flask
Author: Loja Integrada
Author-email: contato@lojaintegrada.com.br
License: LIEULA
Platform: UNKNOWN
Classifier: Development Status :: 2 - Pre-Alpha
Classifier: Intended Audience :: Developers
Classifier: License :: OSI Approved :: MIT License
Classifier: Operating System :: OS Independent
Classifier: Programming Language :: Python
Classifier: Programming Language :: Python :: 2.6
Classifier: Programming Language :: Python :: 2.7
Classifier: Topic :: Software Development :: Libraries :: Python Modules
Classifier: Topic :: Internet
